CMakeLists.txt
LICENSE
MANIFEST.in
README.txt
setup.cfg
setup.py
./include/CLPmod.pxd
./include/clips6_constants.pyi
./include/clips6_exceptions.pyi
./include/clips6_structs.pyi
./include/clips6library.pyi
clips6.egg-info/PKG-INFO
clips6.egg-info/SOURCES.txt
clips6.egg-info/dependency_links.txt
clips6.egg-info/not-zip-safe
clips6.egg-info/requires.txt
clips6.egg-info/top_level.txt
clipssrc/CMakeLists.txt
clipssrc/src/CMakeCache.txt
clipssrc/src/CMakeLists.txt
clipssrc/src/CTestTestfile.cmake
clipssrc/src/Makefile
clipssrc/src/agenda.c
clipssrc/src/agenda.h
clipssrc/src/analysis.c
clipssrc/src/analysis.h
clipssrc/src/argacces.c
clipssrc/src/argacces.h
clipssrc/src/bload.c
clipssrc/src/bload.h
clipssrc/src/bmathfun.c
clipssrc/src/bmathfun.h
clipssrc/src/bsave.c
clipssrc/src/bsave.h
clipssrc/src/classcom.c
clipssrc/src/classcom.h
clipssrc/src/classexm.c
clipssrc/src/classexm.h
clipssrc/src/classfun.c
clipssrc/src/classfun.h
clipssrc/src/classinf.c
clipssrc/src/classinf.h
clipssrc/src/classini.c
clipssrc/src/classini.h
clipssrc/src/classpsr.c
clipssrc/src/classpsr.h
clipssrc/src/clips.h
clipssrc/src/clsltpsr.c
clipssrc/src/clsltpsr.h
clipssrc/src/cmake_install.cmake
clipssrc/src/commline.c
clipssrc/src/commline.h
clipssrc/src/conscomp.c
clipssrc/src/conscomp.h
clipssrc/src/constant.h
clipssrc/src/constrct.c
clipssrc/src/constrct.h
clipssrc/src/constrnt.c
clipssrc/src/constrnt.h
clipssrc/src/crstrtgy.c
clipssrc/src/crstrtgy.h
clipssrc/src/cstrcbin.c
clipssrc/src/cstrcbin.h
clipssrc/src/cstrccmp.h
clipssrc/src/cstrccom.c
clipssrc/src/cstrccom.h
clipssrc/src/cstrcpsr.c
clipssrc/src/cstrcpsr.h
clipssrc/src/cstrnbin.c
clipssrc/src/cstrnbin.h
clipssrc/src/cstrnchk.c
clipssrc/src/cstrnchk.h
clipssrc/src/cstrncmp.c
clipssrc/src/cstrncmp.h
clipssrc/src/cstrnops.c
clipssrc/src/cstrnops.h
clipssrc/src/cstrnpsr.c
clipssrc/src/cstrnpsr.h
clipssrc/src/cstrnutl.c
clipssrc/src/cstrnutl.h
clipssrc/src/default.c
clipssrc/src/default.h
clipssrc/src/defins.c
clipssrc/src/defins.h
clipssrc/src/developr.c
clipssrc/src/developr.h
clipssrc/src/dffctbin.c
clipssrc/src/dffctbin.h
clipssrc/src/dffctbsc.c
clipssrc/src/dffctbsc.h
clipssrc/src/dffctcmp.c
