Metadata-Version: 1.1
Name: clips6
Version: 0.1
Summary: CLIPS Expert System wrapper for the Python
Home-page: https://github.com/vulogov/clips6/
Author: Vladimir Ulogov
Author-email: vladimir.ulogov@me.com
License: GNU GPL Versin 3
Keywords: clips,expert system
Platform: GNU/Linux
Platform: Unix
Platform: Mac OS-X
Classifier: Development Status :: 3 - Alpha
Classifier: Intended Audience :: Developers
Classifier: Intended Audience :: Information Technology
Classifier: License :: OSI Approved :: GNU General Public License v3 (GPLv3)
Classifier: Operating System :: OS Independent
Classifier: Programming Language :: Python :: 2
Classifier: Programming Language :: Python :: 2.4
Classifier: Programming Language :: Python :: 2.5
Classifier: Programming Language :: Python :: 2.6
Classifier: Programming Language :: Python :: 2.7
Classifier: Topic :: Software Development
Classifier: Topic :: Software Development :: Libraries
Classifier: Topic :: Software Development :: Libraries :: Python Modules
Classifier: Topic :: Software Development :: Libraries :: Python Modules
Classifier: Topic :: Scientific/Engineering :: Artificial Intelligence
Requires: msgpack
Requires: PyOpenSSL
